{
  "symbol": "METALIETF",
  "name": "ICICI Prudential Nifty Metal ETF",
  "sector": "Unknown",
  "industry": "Unknown",
  "price": 11.57,
  "change_pct": 1.31,
  "rsi": 44.93,
  "composite_score": -1,
  "macd": {
    "crossover": "bearish",
    "histogram": -0.06
  },
  "ema": {
    "cross_9_21": "bearish",
    "cross_50_200": "bullish",
    "ema50": 11.69,
    "ema200": 10.69
  },
  "breakout": {
    "signal": "none",
    "high_52w": 12.74,
    "low_52w": 7.35,
    "pct_from_high": -9.18,
    "pct_from_low": 57.41
  },
  "volume": {
    "ratio": 0.17,
    "signal": "dry",
    "latest": 2449221,
    "avg_20d": 14838584
  },
  "bollinger": {
    "signal": "neutral"
  },
  "returns": {
    "1d": 0.0,
    "1w": 2.03,
    "1m": -2.69,
    "3m": 9.77
  },
  "fundamentals": {},
  "fund_holdings": {},
  "catalysts": [
    {
      "type": "volume_dryup",
      "symbol": "METALIETF",
      "severity": "low",
      "direction": "neutral",
      "title": "Volume Dry-Up: 0.10x avg",
      "detail": "Extremely low volume \u2014 may indicate consolidation before a move",
      "value": 0.09752074388434072,
      "date": "",
      "priority": 3
    }
  ],
  "matched_scans": [
    "pocket_pivot",
    "gap_up_3pct",
    "preset_volume_3x_spike",
    "preset_volume_2x_spike",
    "preset_above_200_ema",
    "preset_pocket_pivot_volume",
    "preset_supertrend_negative"
  ],
  "circuit": {
    "symbol": "METALIETF",
    "band": "Unknown",
    "upper_limit": 0.0,
    "lower_limit": 0.0,
    "close_price": 0.0,
    "is_restricted": false,
    "band_changed": false,
    "prev_band": "",
    "change_direction": "",
    "in_fno": false
  },
  "earnings_alert": null,
  "oneil": {},
  "guru_ratings": [],
  "surveillance": {},
  "price_history": [
    {
      "date": "2025-03-20",
      "o": 9.15,
      "h": 9.35,
      "l": 9.1,
      "c": 9.25,
      "v": 6444708.0
    },
    {
      "date": "2025-03-21",
      "o": 9.24,
      "h": 9.38,
      "l": 9.17,
      "c": 9.21,
      "v": 2674096.0
    },
    {
      "date": "2025-03-24",
      "o": 9.2,
      "h": 9.33,
      "l": 9.15,
      "c": 9.25,
      "v": 3560295.0
    },
    {
      "date": "2025-03-25",
      "o": 9.3,
      "h": 9.31,
      "l": 9.09,
      "c": 9.12,
      "v": 4003556.0
    },
    {
      "date": "2025-03-26",
      "o": 9.15,
      "h": 9.27,
      "l": 9.02,
      "c": 9.08,
      "v": 4842825.0
    },
    {
      "date": "2025-03-27",
      "o": 9.02,
      "h": 9.19,
      "l": 9.01,
      "c": 9.16,
      "v": 8565143.0
    },
    {
      "date": "2025-03-28",
      "o": 9.19,
      "h": 9.34,
      "l": 9.05,
      "c": 9.08,
      "v": 1898032.0
    },
    {
      "date": "2025-04-01",
      "o": 9.08,
      "h": 9.2,
      "l": 8.98,
      "c": 9.01,
      "v": 1295959.0
    },
    {
      "date": "2025-04-02",
      "o": 9.01,
      "h": 9.1,
      "l": 8.93,
      "c": 9.07,
      "v": 2078308.0
    },
    {
      "date": "2025-04-03",
      "o": 9.01,
      "h": 9.08,
      "l": 8.97,
      "c": 9.0,
      "v": 1856952.0
    },
    {
      "date": "2025-04-04",
      "o": 9.0,
      "h": 9.01,
      "l": 8.4,
      "c": 8.46,
      "v": 9856542.0
    },
    {
      "date": "2025-04-07",
      "o": 8.46,
      "h": 8.46,
      "l": 7.35,
      "c": 7.9,
      "v": 14754400.0
    },
    {
      "date": "2025-04-08",
      "o": 8.09,
      "h": 8.39,
      "l": 7.82,
      "c": 7.98,
      "v": 3928779.0
    },
    {
      "date": "2025-04-09",
      "o": 8.05,
      "h": 8.07,
      "l": 7.79,
      "c": 7.86,
      "v": 6754823.0
    },
    {
      "date": "2025-04-11",
      "o": 7.9,
      "h": 8.44,
      "l": 7.9,
      "c": 8.16,
      "v": 6292358.0
    },
    {
      "date": "2025-04-15",
      "o": 8.25,
      "h": 8.44,
      "l": 8.22,
      "c": 8.43,
      "v": 4071586.0
    },
    {
      "date": "2025-04-16",
      "o": 8.46,
      "h": 8.54,
      "l": 8.34,
      "c": 8.44,
      "v": 5329339.0
    },
    {
      "date": "2025-04-17",
      "o": 8.48,
      "h": 8.55,
      "l": 8.34,
      "c": 8.5,
      "v": 4470261.0
    },
    {
      "date": "2025-04-21",
      "o": 8.66,
      "h": 8.75,
      "l": 8.5,
      "c": 8.66,
      "v": 16463210.0
    },
    {
      "date": "2025-04-22",
      "o": 8.8,
      "h": 8.82,
      "l": 8.67,
      "c": 8.68,
      "v": 7055198.0
    },
    {
      "date": "2025-04-23",
      "o": 8.85,
      "h": 8.85,
      "l": 8.61,
      "c": 8.74,
      "v": 4454349.0
    },
    {
      "date": "2025-04-24",
      "o": 8.73,
      "h": 8.82,
      "l": 8.7,
      "c": 8.77,
      "v": 3057027.0
    },
    {
      "date": "2025-04-25",
      "o": 8.79,
      "h": 8.83,
      "l": 8.5,
      "c": 8.58,
      "v": 8665520.0
    },
    {
      "date": "2025-04-28",
      "o": 8.62,
      "h": 8.72,
      "l": 8.52,
      "c": 8.69,
      "v": 2892409.0
    },
    {
      "date": "2025-04-29",
      "o": 8.74,
      "h": 8.77,
      "l": 8.61,
      "c": 8.62,
      "v": 3074505.0
    },
    {
      "date": "2025-04-30",
      "o": 8.65,
      "h": 8.68,
      "l": 8.55,
      "c": 8.57,
      "v": 5930523.0
    },
    {
      "date": "2025-05-02",
      "o": 8.64,
      "h": 8.72,
      "l": 8.47,
      "c": 8.53,
      "v": 10750460.0
    },
    {
      "date": "2025-05-05",
      "o": 8.7,
      "h": 8.7,
      "l": 8.52,
      "c": 8.6,
      "v": 5625900.0
    },
    {
      "date": "2025-05-06",
      "o": 8.66,
      "h": 8.66,
      "l": 8.51,
      "c": 8.52,
      "v": 4003835.0
    },
    {
      "date": "2025-05-07",
      "o": 8.5,
      "h": 8.64,
      "l": 8.44,
      "c": 8.61,
      "v": 4506873.0
    },
    {
      "date": "2025-05-08",
      "o": 8.62,
      "h": 8.66,
      "l": 8.41,
      "c": 8.44,
      "v": 6101476.0
    },
    {
      "date": "2025-05-09",
      "o": 8.41,
      "h": 8.46,
      "l": 8.29,
      "c": 8.43,
      "v": 4762652.0
    },
    {
      "date": "2025-05-12",
      "o": 8.52,
      "h": 8.92,
      "l": 8.52,
      "c": 8.9,
      "v": 15086510.0
    },
    {
      "date": "2025-05-13",
      "o": 8.9,
      "h": 8.94,
      "l": 8.8,
      "c": 8.82,
      "v": 4838336.0
    },
    {
      "date": "2025-05-14",
      "o": 8.84,
      "h": 9.08,
      "l": 8.82,
      "c": 9.04,
      "v": 16694000.0
    },
    {
      "date": "2025-05-15",
      "o": 9.07,
      "h": 9.21,
      "l": 9.03,
      "c": 9.19,
      "v": 10114370.0
    },
    {
      "date": "2025-05-16",
      "o": 9.19,
      "h": 9.28,
      "l": 9.12,
      "c": 9.18,
      "v": 3888844.0
    },
    {
      "date": "2025-05-19",
      "o": 9.17,
      "h": 9.24,
      "l": 9.13,
      "c": 9.19,
      "v": 4637269.0
    },
    {
      "date": "2025-05-20",
      "o": 9.3,
      "h": 9.55,
      "l": 9.13,
      "c": 9.14,
      "v": 3010076.0
    },
    {
      "date": "2025-05-21",
      "o": 9.18,
      "h": 9.23,
      "l": 9.11,
      "c": 9.18,
      "v": 3716870.0
    },
    {
      "date": "2025-05-22",
      "o": 9.16,
      "h": 9.23,
      "l": 9.11,
      "c": 9.18,
      "v": 3239176.0
    },
    {
      "date": "2025-05-23",
      "o": 9.05,
      "h": 9.27,
      "l": 9.05,
      "c": 9.23,
      "v": 2296463.0
    },
    {
      "date": "2025-05-26",
      "o": 9.25,
      "h": 9.38,
      "l": 9.25,
      "c": 9.34,
      "v": 3974327.0
    },
    {
      "date": "2025-05-27",
      "o": 9.31,
      "h": 9.38,
      "l": 9.25,
      "c": 9.28,
      "v": 3993457.0
    },
    {
      "date": "2025-05-28",
      "o": 9.32,
      "h": 9.36,
      "l": 9.21,
      "c": 9.22,
      "v": 2594464.0
    },
    {
      "date": "2025-05-29",
      "o": 9.34,
      "h": 9.37,
      "l": 9.26,
      "c": 9.33,
      "v": 4056191.0
    },
    {
      "date": "2025-05-30",
      "o": 9.35,
      "h": 9.38,
      "l": 9.17,
      "c": 9.2,
      "v": 5502674.0
    },
    {
      "date": "2025-06-02",
      "o": 9.17,
      "h": 9.17,
      "l": 9.06,
      "c": 9.11,
      "v": 4399768.0
    },
    {
      "date": "2025-06-03",
      "o": 9.11,
      "h": 9.19,
      "l": 8.88,
      "c": 9.1,
      "v": 2650437.0
    },
    {
      "date": "2025-06-04",
      "o": 9.32,
      "h": 9.32,
      "l": 9.05,
      "c": 9.15,
      "v": 9389590.0
    },
    {
      "date": "2025-06-05",
      "o": 9.41,
      "h": 9.41,
      "l": 9.11,
      "c": 9.21,
      "v": 2552408.0
    },
    {
      "date": "2025-06-06",
      "o": 9.24,
      "h": 9.4,
      "l": 9.21,
      "c": 9.39,
      "v": 5808353.0
    },
    {
      "date": "2025-06-09",
      "o": 9.41,
      "h": 9.51,
      "l": 9.33,
      "c": 9.46,
      "v": 3584018.0
    },
    {
      "date": "2025-06-10",
      "o": 9.52,
      "h": 9.58,
      "l": 9.46,
      "c": 9.49,
      "v": 3897984.0
    },
    {
      "date": "2025-06-11",
      "o": 9.48,
      "h": 9.56,
      "l": 9.46,
      "c": 9.46,
      "v": 3781748.0
    },
    {
      "date": "2025-06-12",
      "o": 9.51,
      "h": 9.54,
      "l": 9.31,
      "c": 9.33,
      "v": 3764358.0
    },
    {
      "date": "2025-06-13",
      "o": 9.3,
      "h": 9.3,
      "l": 9.13,
      "c": 9.25,
      "v": 3428306.0
    },
    {
      "date": "2025-06-16",
      "o": 9.48,
      "h": 9.49,
      "l": 9.15,
      "c": 9.35,
      "v": 3082105.0
    },
    {
      "date": "2025-06-17",
      "o": 9.11,
      "h": 9.4,
      "l": 9.11,
      "c": 9.21,
      "v": 3111624.0
    },
    {
      "date": "2025-06-18",
      "o": 9.49,
      "h": 9.49,
      "l": 9.13,
      "c": 9.16,
      "v": 1696950.0
    },
    {
      "date": "2025-06-19",
      "o": 9.22,
      "h": 9.22,
      "l": 9.01,
      "c": 9.05,
      "v": 2982993.0
    },
    {
      "date": "2025-06-20",
      "o": 9.03,
      "h": 9.19,
      "l": 9.03,
      "c": 9.15,
      "v": 2446518.0
    },
    {
      "date": "2025-06-23",
      "o": 9.15,
      "h": 9.24,
      "l": 9.07,
      "c": 9.19,
      "v": 2757969.0
    },
    {
      "date": "2025-06-24",
      "o": 9.24,
      "h": 9.4,
      "l": 9.24,
      "c": 9.3,
      "v": 2945422.0
    },
    {
      "date": "2025-06-25",
      "o": 9.41,
      "h": 9.47,
      "l": 9.32,
      "c": 9.33,
      "v": 1419940.0
    },
    {
      "date": "2025-06-26",
      "o": 9.56,
      "h": 9.56,
      "l": 9.33,
      "c": 9.54,
      "v": 5227893.0
    },
    {
      "date": "2025-06-27",
      "o": 9.77,
      "h": 9.77,
      "l": 9.49,
      "c": 9.58,
      "v": 4011314.0
    },
    {
      "date": "2025-06-30",
      "o": 9.34,
      "h": 9.69,
      "l": 9.34,
      "c": 9.56,
      "v": 5733019.0
    },
    {
      "date": "2025-07-01",
      "o": 9.6,
      "h": 9.62,
      "l": 9.48,
      "c": 9.58,
      "v": 3085497.0
    },
    {
      "date": "2025-07-02",
      "o": 9.81,
      "h": 9.81,
      "l": 9.57,
      "c": 9.71,
      "v": 7573618.0
    },
    {
      "date": "2025-07-03",
      "o": 9.8,
      "h": 9.8,
      "l": 9.63,
      "c": 9.64,
      "v": 5293945.0
    },
    {
      "date": "2025-07-04",
      "o": 9.88,
      "h": 9.88,
      "l": 9.55,
      "c": 9.6,
      "v": 5872270.0
    },
    {
      "date": "2025-07-07",
      "o": 9.5,
      "h": 9.68,
      "l": 9.36,
      "c": 9.53,
      "v": 2144350.0
    },
    {
      "date": "2025-07-08",
      "o": 9.61,
      "h": 9.61,
      "l": 9.5,
      "c": 9.52,
      "v": 3843383.0
    },
    {
      "date": "2025-07-09",
      "o": 9.59,
      "h": 9.59,
      "l": 9.28,
      "c": 9.4,
      "v": 5417713.0
    },
    {
      "date": "2025-07-10",
      "o": 9.63,
      "h": 9.63,
      "l": 9.38,
      "c": 9.44,
      "v": 2390301.0
    },
    {
      "date": "2025-07-11",
      "o": 9.58,
      "h": 9.58,
      "l": 9.39,
      "c": 9.4,
      "v": 1829452.0
    },
    {
      "date": "2025-07-14",
      "o": 9.39,
      "h": 9.49,
      "l": 9.38,
      "c": 9.44,
      "v": 1752244.0
    },
    {
      "date": "2025-07-15",
      "o": 9.49,
      "h": 9.6,
      "l": 9.37,
      "c": 9.43,
      "v": 2746941.0
    },
    {
      "date": "2025-07-16",
      "o": 9.19,
      "h": 9.45,
      "l": 9.19,
      "c": 9.39,
      "v": 1933220.0
    },
    {
      "date": "2025-07-17",
      "o": 9.62,
      "h": 9.62,
      "l": 9.39,
      "c": 9.44,
      "v": 1934819.0
    },
    {
      "date": "2025-07-18",
      "o": 9.54,
      "h": 9.54,
      "l": 9.42,
      "c": 9.48,
      "v": 3424688.0
    },
    {
      "date": "2025-07-21",
      "o": 9.7,
      "h": 9.7,
      "l": 9.44,
      "c": 9.57,
      "v": 2277646.0
    },
    {
      "date": "2025-07-22",
      "o": 9.7,
      "h": 9.7,
      "l": 9.53,
      "c": 9.54,
      "v": 1651823.0
    },
    {
      "date": "2025-07-23",
      "o": 9.77,
      "h": 9.77,
      "l": 9.52,
      "c": 9.58,
      "v": 2179621.0
    },
    {
      "date": "2025-07-24",
      "o": 9.41,
      "h": 9.7,
      "l": 9.41,
      "c": 9.58,
      "v": 2904765.0
    },
    {
      "date": "2025-07-25",
      "o": 9.58,
      "h": 9.62,
      "l": 9.41,
      "c": 9.43,
      "v": 2956289.0
    },
    {
      "date": "2025-07-28",
      "o": 9.43,
      "h": 9.48,
      "l": 9.3,
      "c": 9.31,
      "v": 2524172.0
    },
    {
      "date": "2025-07-29",
      "o": 9.07,
      "h": 9.45,
      "l": 9.07,
      "c": 9.42,
      "v": 1245735.0
    },
    {
      "date": "2025-07-30",
      "o": 9.41,
      "h": 9.49,
      "l": 9.39,
      "c": 9.41,
      "v": 1467961.0
    },
    {
      "date": "2025-07-31",
      "o": 9.35,
      "h": 9.41,
      "l": 9.24,
      "c": 9.29,
      "v": 1333530.0
    },
    {
      "date": "2025-08-01",
      "o": 9.3,
      "h": 9.34,
      "l": 9.1,
      "c": 9.11,
      "v": 2079933.0
    },
    {
      "date": "2025-08-04",
      "o": 9.33,
      "h": 9.38,
      "l": 9.11,
      "c": 9.32,
      "v": 3568341.0
    },
    {
      "date": "2025-08-05",
      "o": 9.39,
      "h": 9.39,
      "l": 9.3,
      "c": 9.33,
      "v": 4170345.0
    },
    {
      "date": "2025-08-06",
      "o": 9.37,
      "h": 9.38,
      "l": 9.26,
      "c": 9.3,
      "v": 855298.0
    },
    {
      "date": "2025-08-07",
      "o": 9.3,
      "h": 9.35,
      "l": 9.17,
      "c": 9.31,
      "v": 2783801.0
    },
    {
      "date": "2025-08-08",
      "o": 9.37,
      "h": 9.37,
      "l": 9.16,
      "c": 9.18,
      "v": 2107838.0
    },
    {
      "date": "2025-08-11",
      "o": 9.19,
      "h": 9.25,
      "l": 9.15,
      "c": 9.23,
      "v": 613446.0
    },
    {
      "date": "2025-08-12",
      "o": 9.46,
      "h": 9.46,
      "l": 9.16,
      "c": 9.24,
      "v": 1822802.0
    },
    {
      "date": "2025-08-13",
      "o": 9.29,
      "h": 9.44,
      "l": 9.29,
      "c": 9.38,
      "v": 1758746.0
    },
    {
      "date": "2025-08-14",
      "o": 9.14,
      "h": 9.42,
      "l": 9.14,
      "c": 9.26,
      "v": 1321307.0
    },
    {
      "date": "2025-08-18",
      "o": 9.42,
      "h": 9.43,
      "l": 9.31,
      "c": 9.41,
      "v": 1478024.0
    },
    {
      "date": "2025-08-19",
      "o": 9.6,
      "h": 9.6,
      "l": 8.98,
      "c": 9.48,
      "v": 2666335.0
    },
    {
      "date": "2025-08-20",
      "o": 9.6,
      "h": 9.6,
      "l": 9.43,
      "c": 9.51,
      "v": 1753969.0
    },
    {
      "date": "2025-08-21",
      "o": 9.6,
      "h": 9.6,
      "l": 9.5,
      "c": 9.51,
      "v": 625145.0
    },
    {
      "date": "2025-08-22",
      "o": 9.51,
      "h": 9.55,
      "l": 9.4,
      "c": 9.4,
      "v": 932945.0
    },
    {
      "date": "2025-08-25",
      "o": 9.51,
      "h": 9.52,
      "l": 9.2,
      "c": 9.46,
      "v": 1015503.0
    },
    {
      "date": "2025-08-26",
      "o": 9.48,
      "h": 9.48,
      "l": 9.28,
      "c": 9.3,
      "v": 1022451.0
    },
    {
      "date": "2025-08-28",
      "o": 9.34,
      "h": 9.37,
      "l": 9.22,
      "c": 9.25,
      "v": 3835036.0
    },
    {
      "date": "2025-08-29",
      "o": 9.28,
      "h": 9.32,
      "l": 9.18,
      "c": 9.21,
      "v": 1513011.0
    },
    {
      "date": "2025-09-01",
      "o": 9.24,
      "h": 9.38,
      "l": 9.21,
      "c": 9.36,
      "v": 2440087.0
    },
    {
      "date": "2025-09-02",
      "o": 9.36,
      "h": 9.48,
      "l": 9.3,
      "c": 9.42,
      "v": 1213826.0
    },
    {
      "date": "2025-09-03",
      "o": 9.6,
      "h": 9.74,
      "l": 9.2,
      "c": 9.72,
      "v": 18083350.0
    },
    {
      "date": "2025-09-04",
      "o": 9.72,
      "h": 9.9,
      "l": 9.65,
      "c": 9.65,
      "v": 14808210.0
    },
    {
      "date": "2025-09-05",
      "o": 9.87,
      "h": 10.2,
      "l": 9.32,
      "c": 9.73,
      "v": 2131754.0
    },
    {
      "date": "2025-09-08",
      "o": 9.84,
      "h": 9.87,
      "l": 9.67,
      "c": 9.77,
      "v": 5577194.0
    },
    {
      "date": "2025-09-09",
      "o": 10.01,
      "h": 10.01,
      "l": 9.72,
      "c": 9.76,
      "v": 1916939.0
    },
    {
      "date": "2025-09-10",
      "o": 9.78,
      "h": 9.87,
      "l": 9.76,
      "c": 9.78,
      "v": 1924533.0
    },
    {
      "date": "2025-09-11",
      "o": 9.78,
      "h": 9.89,
      "l": 9.76,
      "c": 9.83,
      "v": 4924012.0
    },
    {
      "date": "2025-09-12",
      "o": 9.58,
      "h": 10.2,
      "l": 9.58,
      "c": 9.92,
      "v": 2458317.0
    },
    {
      "date": "2025-09-15",
      "o": 10.16,
      "h": 10.16,
      "l": 9.7,
      "c": 9.93,
      "v": 3224303.0
    },
    {
      "date": "2025-09-16",
      "o": 9.93,
      "h": 10.11,
      "l": 9.7,
      "c": 10.01,
      "v": 5209365.0
    },
    {
      "date": "2025-09-17",
      "o": 9.8,
      "h": 10.2,
      "l": 9.75,
      "c": 9.96,
      "v": 3749531.0
    },
    {
      "date": "2025-09-18",
      "o": 9.96,
      "h": 10.03,
      "l": 9.91,
      "c": 10.01,
      "v": 5267424.0
    },
    {
      "date": "2025-09-19",
      "o": 10.01,
      "h": 10.08,
      "l": 9.96,
      "c": 10.01,
      "v": 4196887.0
    },
    {
      "date": "2025-09-22",
      "o": 10.0,
      "h": 10.11,
      "l": 9.93,
      "c": 10.04,
      "v": 2959644.0
    },
    {
      "date": "2025-09-23",
      "o": 10.18,
      "h": 10.45,
      "l": 9.94,
      "c": 10.18,
      "v": 9937450.0
    },
    {
      "date": "2025-09-24",
      "o": 10.18,
      "h": 10.6,
      "l": 10.08,
      "c": 10.1,
      "v": 3777782.0
    },
    {
      "date": "2025-09-25",
      "o": 10.2,
      "h": 10.23,
      "l": 10.1,
      "c": 10.12,
      "v": 3171051.0
    },
    {
      "date": "2025-09-26",
      "o": 10.25,
      "h": 10.25,
      "l": 9.9,
      "c": 9.93,
      "v": 4535666.0
    },
    {
      "date": "2025-09-29",
      "o": 10.02,
      "h": 10.05,
      "l": 9.95,
      "c": 9.97,
      "v": 2907694.0
    },
    {
      "date": "2025-09-30",
      "o": 10.21,
      "h": 10.21,
      "l": 9.9,
      "c": 10.11,
      "v": 3278925.0
    },
    {
      "date": "2025-10-01",
      "o": 9.85,
      "h": 10.38,
      "l": 9.85,
      "c": 10.15,
      "v": 5611637.0
    },
    {
      "date": "2025-10-03",
      "o": 10.25,
      "h": 10.46,
      "l": 10.11,
      "c": 10.35,
      "v": 32821460.0
    },
    {
      "date": "2025-10-06",
      "o": 10.35,
      "h": 10.44,
      "l": 10.19,
      "c": 10.23,
      "v": 12205860.0
    },
    {
      "date": "2025-10-07",
      "o": 10.48,
      "h": 10.58,
      "l": 10.2,
      "c": 10.21,
      "v": 10687400.0
    },
    {
      "date": "2025-10-08",
      "o": 10.28,
      "h": 10.28,
      "l": 10.13,
      "c": 10.19,
      "v": 4862318.0
    },
    {
      "date": "2025-10-09",
      "o": 10.25,
      "h": 10.45,
      "l": 10.19,
      "c": 10.42,
      "v": 22541540.0
    },
    {
      "date": "2025-10-10",
      "o": 10.42,
      "h": 10.46,
      "l": 10.27,
      "c": 10.32,
      "v": 11452750.0
    },
    {
      "date": "2025-10-13",
      "o": 10.33,
      "h": 10.33,
      "l": 10.2,
      "c": 10.27,
      "v": 7478249.0
    },
    {
      "date": "2025-10-14",
      "o": 10.38,
      "h": 10.39,
      "l": 10.08,
      "c": 10.14,
      "v": 28582140.0
    },
    {
      "date": "2025-10-15",
      "o": 10.44,
      "h": 10.56,
      "l": 10.13,
      "c": 10.28,
      "v": 8342507.0
    },
    {
      "date": "2025-10-16",
      "o": 10.32,
      "h": 10.35,
      "l": 10.25,
      "c": 10.34,
      "v": 10141600.0
    },
    {
      "date": "2025-10-17",
      "o": 10.0,
      "h": 10.37,
      "l": 10.0,
      "c": 10.26,
      "v": 7868490.0
    },
    {
      "date": "2025-10-20",
      "o": 10.35,
      "h": 10.35,
      "l": 10.17,
      "c": 10.23,
      "v": 6213121.0
    },
    {
      "date": "2025-10-21",
      "o": 10.38,
      "h": 10.4,
      "l": 10.24,
      "c": 10.38,
      "v": 3733236.0
    },
    {
      "date": "2025-10-23",
      "o": 10.43,
      "h": 10.44,
      "l": 10.26,
      "c": 10.28,
      "v": 8093425.0
    },
    {
      "date": "2025-10-24",
      "o": 10.38,
      "h": 10.52,
      "l": 10.36,
      "c": 10.41,
      "v": 21707540.0
    },
    {
      "date": "2025-10-27",
      "o": 10.48,
      "h": 10.57,
      "l": 10.46,
      "c": 10.53,
      "v": 13398740.0
    },
    {
      "date": "2025-10-28",
      "o": 10.55,
      "h": 10.7,
      "l": 10.52,
      "c": 10.66,
      "v": 23976500.0
    },
    {
      "date": "2025-10-29",
      "o": 10.75,
      "h": 10.9,
      "l": 10.68,
      "c": 10.83,
      "v": 23756890.0
    },
    {
      "date": "2025-10-30",
      "o": 10.83,
      "h": 11.05,
      "l": 10.64,
      "c": 10.78,
      "v": 10650970.0
    },
    {
      "date": "2025-10-31",
      "o": 10.81,
      "h": 10.82,
      "l": 10.64,
      "c": 10.68,
      "v": 16880780.0
    },
    {
      "date": "2025-11-03",
      "o": 10.73,
      "h": 10.78,
      "l": 10.66,
      "c": 10.72,
      "v": 9269071.0
    },
    {
      "date": "2025-11-04",
      "o": 10.98,
      "h": 10.98,
      "l": 10.52,
      "c": 10.54,
      "v": 11492420.0
    },
    {
      "date": "2025-11-06",
      "o": 10.79,
      "h": 10.86,
      "l": 10.27,
      "c": 10.33,
      "v": 40038620.0
    },
    {
      "date": "2025-11-07",
      "o": 10.29,
      "h": 10.55,
      "l": 10.22,
      "c": 10.48,
      "v": 14524960.0
    },
    {
      "date": "2025-11-10",
      "o": 10.51,
      "h": 10.63,
      "l": 10.48,
      "c": 10.55,
      "v": 17513190.0
    },
    {
      "date": "2025-11-11",
      "o": 10.58,
      "h": 10.65,
      "l": 10.46,
      "c": 10.62,
      "v": 18491330.0
    },
    {
      "date": "2025-11-12",
      "o": 10.63,
      "h": 10.71,
      "l": 10.59,
      "c": 10.6,
      "v": 10296830.0
    },
    {
      "date": "2025-11-13",
      "o": 10.72,
      "h": 10.76,
      "l": 10.61,
      "c": 10.64,
      "v": 9628926.0
    },
    {
      "date": "2025-11-14",
      "o": 10.68,
      "h": 10.68,
      "l": 10.49,
      "c": 10.53,
      "v": 7334742.0
    },
    {
      "date": "2025-11-17",
      "o": 10.53,
      "h": 10.63,
      "l": 10.5,
      "c": 10.56,
      "v": 5242479.0
    },
    {
      "date": "2025-11-18",
      "o": 10.56,
      "h": 10.76,
      "l": 10.37,
      "c": 10.44,
      "v": 10620140.0
    },
    {
      "date": "2025-11-19",
      "o": 10.44,
      "h": 10.47,
      "l": 10.4,
      "c": 10.42,
      "v": 9024489.0
    },
    {
      "date": "2025-11-20",
      "o": 10.42,
      "h": 10.52,
      "l": 10.41,
      "c": 10.42,
      "v": 7339714.0
    },
    {
      "date": "2025-11-21",
      "o": 10.5,
      "h": 10.5,
      "l": 10.15,
      "c": 10.18,
      "v": 10961570.0
    },
    {
      "date": "2025-11-24",
      "o": 10.22,
      "h": 10.27,
      "l": 10.04,
      "c": 10.06,
      "v": 5623601.0
    },
    {
      "date": "2025-11-25",
      "o": 10.25,
      "h": 10.25,
      "l": 10.06,
      "c": 10.12,
      "v": 6126371.0
    },
    {
      "date": "2025-11-26",
      "o": 10.13,
      "h": 10.34,
      "l": 10.13,
      "c": 10.32,
      "v": 6300276.0
    },
    {
      "date": "2025-11-27",
      "o": 10.41,
      "h": 10.44,
      "l": 10.25,
      "c": 10.32,
      "v": 11242340.0
    },
    {
      "date": "2025-11-28",
      "o": 10.63,
      "h": 10.63,
      "l": 10.3,
      "c": 10.34,
      "v": 4876176.0
    },
    {
      "date": "2025-12-01",
      "o": 10.59,
      "h": 10.59,
      "l": 10.35,
      "c": 10.4,
      "v": 13236200.0
    },
    {
      "date": "2025-12-02",
      "o": 10.63,
      "h": 10.63,
      "l": 10.33,
      "c": 10.36,
      "v": 5367329.0
    },
    {
      "date": "2025-12-03",
      "o": 10.4,
      "h": 10.4,
      "l": 10.22,
      "c": 10.29,
      "v": 7524667.0
    },
    {
      "date": "2025-12-04",
      "o": 10.35,
      "h": 10.42,
      "l": 10.3,
      "c": 10.31,
      "v": 10288150.0
    },
    {
      "date": "2025-12-05",
      "o": 10.42,
      "h": 10.42,
      "l": 10.21,
      "c": 10.38,
      "v": 4701547.0
    },
    {
      "date": "2025-12-08",
      "o": 10.38,
      "h": 10.44,
      "l": 10.15,
      "c": 10.18,
      "v": 12236620.0
    },
    {
      "date": "2025-12-09",
      "o": 10.43,
      "h": 10.43,
      "l": 10.0,
      "c": 10.15,
      "v": 8042754.0
    },
    {
      "date": "2025-12-10",
      "o": 10.4,
      "h": 10.54,
      "l": 10.08,
      "c": 10.2,
      "v": 5850035.0
    },
    {
      "date": "2025-12-11",
      "o": 10.2,
      "h": 10.34,
      "l": 10.2,
      "c": 10.32,
      "v": 9743127.0
    },
    {
      "date": "2025-12-12",
      "o": 10.57,
      "h": 10.61,
      "l": 10.32,
      "c": 10.58,
      "v": 15194780.0
    },
    {
      "date": "2025-12-15",
      "o": 10.62,
      "h": 10.64,
      "l": 10.51,
      "c": 10.6,
      "v": 9424081.0
    },
    {
      "date": "2025-12-16",
      "o": 10.6,
      "h": 10.69,
      "l": 10.43,
      "c": 10.51,
      "v": 13526670.0
    },
    {
      "date": "2025-12-17",
      "o": 10.77,
      "h": 10.77,
      "l": 10.5,
      "c": 10.53,
      "v": 5891961.0
    },
    {
      "date": "2025-12-18",
      "o": 10.56,
      "h": 10.63,
      "l": 10.47,
      "c": 10.54,
      "v": 6445969.0
    },
    {
      "date": "2025-12-19",
      "o": 10.57,
      "h": 10.6,
      "l": 10.5,
      "c": 10.57,
      "v": 11438410.0
    },
    {
      "date": "2025-12-22",
      "o": 10.57,
      "h": 10.79,
      "l": 10.57,
      "c": 10.71,
      "v": 55027710.0
    },
    {
      "date": "2025-12-23",
      "o": 10.71,
      "h": 10.97,
      "l": 10.71,
      "c": 10.77,
      "v": 17192380.0
    },
    {
      "date": "2025-12-24",
      "o": 11.03,
      "h": 11.03,
      "l": 10.74,
      "c": 10.77,
      "v": 38407100.0
    },
    {
      "date": "2025-12-26",
      "o": 11.03,
      "h": 11.03,
      "l": 10.78,
      "c": 10.85,
      "v": 11286810.0
    },
    {
      "date": "2025-12-29",
      "o": 11.09,
      "h": 11.09,
      "l": 10.31,
      "c": 10.83,
      "v": 54138860.0
    },
    {
      "date": "2025-12-30",
      "o": 11.1,
      "h": 11.11,
      "l": 10.81,
      "c": 11.06,
      "v": 48879000.0
    },
    {
      "date": "2025-12-31",
      "o": 11.33,
      "h": 11.33,
      "l": 11.08,
      "c": 11.23,
      "v": 70203430.0
    },
    {
      "date": "2026-01-01",
      "o": 11.44,
      "h": 11.44,
      "l": 11.2,
      "c": 11.31,
      "v": 25582600.0
    },
    {
      "date": "2026-01-02",
      "o": 11.59,
      "h": 11.75,
      "l": 11.32,
      "c": 11.48,
      "v": 50829500.0
    },
    {
      "date": "2026-01-05",
      "o": 11.76,
      "h": 11.78,
      "l": 11.47,
      "c": 11.55,
      "v": 43747340.0
    },
    {
      "date": "2026-01-06",
      "o": 11.83,
      "h": 11.96,
      "l": 11.52,
      "c": 11.58,
      "v": 51144070.0
    },
    {
      "date": "2026-01-07",
      "o": 11.55,
      "h": 11.86,
      "l": 11.55,
      "c": 11.58,
      "v": 25586970.0
    },
    {
      "date": "2026-01-08",
      "o": 11.58,
      "h": 11.86,
      "l": 11.12,
      "c": 11.17,
      "v": 41641160.0
    },
    {
      "date": "2026-01-09",
      "o": 11.44,
      "h": 11.44,
      "l": 11.06,
      "c": 11.13,
      "v": 61457260.0
    },
    {
      "date": "2026-01-12",
      "o": 11.4,
      "h": 11.4,
      "l": 11.09,
      "c": 11.37,
      "v": 29397700.0
    },
    {
      "date": "2026-01-13",
      "o": 11.28,
      "h": 11.57,
      "l": 11.08,
      "c": 11.41,
      "v": 20937930.0
    },
    {
      "date": "2026-01-14",
      "o": 11.12,
      "h": 11.77,
      "l": 11.12,
      "c": 11.72,
      "v": 41431690.0
    },
    {
      "date": "2026-01-16",
      "o": 12.01,
      "h": 12.08,
      "l": 11.42,
      "c": 11.65,
      "v": 41529680.0
    },
    {
      "date": "2026-01-19",
      "o": 11.85,
      "h": 11.85,
      "l": 11.61,
      "c": 11.65,
      "v": 30248410.0
    },
    {
      "date": "2026-01-20",
      "o": 11.94,
      "h": 11.94,
      "l": 11.2,
      "c": 11.41,
      "v": 41005800.0
    },
    {
      "date": "2026-01-21",
      "o": 11.45,
      "h": 11.56,
      "l": 11.12,
      "c": 11.5,
      "v": 31858520.0
    },
    {
      "date": "2026-01-22",
      "o": 11.78,
      "h": 11.78,
      "l": 11.49,
      "c": 11.6,
      "v": 26025170.0
    },
    {
      "date": "2026-01-23",
      "o": 11.89,
      "h": 11.95,
      "l": 11.5,
      "c": 11.52,
      "v": 25899720.0
    },
    {
      "date": "2026-01-27",
      "o": 11.8,
      "h": 12.08,
      "l": 11.53,
      "c": 11.89,
      "v": 31115900.0
    },
    {
      "date": "2026-01-28",
      "o": 12.18,
      "h": 12.65,
      "l": 11.89,
      "c": 12.18,
      "v": 67211620.0
    },
    {
      "date": "2026-01-29",
      "o": 12.48,
      "h": 12.69,
      "l": 12.06,
      "c": 12.56,
      "v": 84601870.0
    },
    {
      "date": "2026-01-30",
      "o": 12.53,
      "h": 12.53,
      "l": 11.8,
      "c": 11.85,
      "v": 74117510.0
    },
    {
      "date": "2026-02-02",
      "o": 11.56,
      "h": 11.8,
      "l": 11.18,
      "c": 11.64,
      "v": 31270630.0
    },
    {
      "date": "2026-02-03",
      "o": 12.1,
      "h": 12.5,
      "l": 11.78,
      "c": 11.94,
      "v": 31437180.0
    },
    {
      "date": "2026-02-04",
      "o": 12.23,
      "h": 12.5,
      "l": 11.99,
      "c": 12.05,
      "v": 19805370.0
    },
    {
      "date": "2026-02-05",
      "o": 12.35,
      "h": 12.35,
      "l": 11.77,
      "c": 11.96,
      "v": 17841420.0
    },
    {
      "date": "2026-02-06",
      "o": 11.96,
      "h": 12.25,
      "l": 11.79,
      "c": 11.97,
      "v": 13986120.0
    },
    {
      "date": "2026-02-09",
      "o": 12.26,
      "h": 12.5,
      "l": 12.02,
      "c": 12.15,
      "v": 43584380.0
    },
    {
      "date": "2026-02-10",
      "o": 12.45,
      "h": 12.45,
      "l": 12.14,
      "c": 12.28,
      "v": 18877590.0
    },
    {
      "date": "2026-02-11",
      "o": 11.97,
      "h": 12.5,
      "l": 11.97,
      "c": 12.3,
      "v": 16387530.0
    },
    {
      "date": "2026-02-12",
      "o": 12.5,
      "h": 12.5,
      "l": 11.99,
      "c": 12.3,
      "v": 13579790.0
    },
    {
      "date": "2026-02-13",
      "o": 12.6,
      "h": 12.6,
      "l": 11.16,
      "c": 11.95,
      "v": 20865170.0
    },
    {
      "date": "2026-02-16",
      "o": 12.24,
      "h": 12.24,
      "l": 11.85,
      "c": 11.98,
      "v": 10940580.0
    },
    {
      "date": "2026-02-17",
      "o": 11.9,
      "h": 12.3,
      "l": 11.76,
      "c": 11.85,
      "v": 20159350.0
    },
    {
      "date": "2026-02-18",
      "o": 11.84,
      "h": 12.14,
      "l": 11.84,
      "c": 12.04,
      "v": 16037120.0
    },
    {
      "date": "2026-02-19",
      "o": 11.75,
      "h": 12.3,
      "l": 11.75,
      "c": 11.89,
      "v": 10132770.0
    },
    {
      "date": "2026-02-20",
      "o": 12.18,
      "h": 12.18,
      "l": 11.6,
      "c": 12.01,
      "v": 10317480.0
    },
    {
      "date": "2026-02-23",
      "o": 12.01,
      "h": 12.3,
      "l": 11.93,
      "c": 11.99,
      "v": 11972970.0
    },
    {
      "date": "2026-02-24",
      "o": 11.69,
      "h": 12.2,
      "l": 11.69,
      "c": 12.11,
      "v": 14054610.0
    },
    {
      "date": "2026-02-25",
      "o": 11.8,
      "h": 12.46,
      "l": 11.8,
      "c": 12.43,
      "v": 28201650.0
    },
    {
      "date": "2026-02-26",
      "o": 12.11,
      "h": 12.74,
      "l": 12.1,
      "c": 12.47,
      "v": 13556310.0
    },
    {
      "date": "2026-02-27",
      "o": 12.6,
      "h": 12.6,
      "l": 12.26,
      "c": 12.3,
      "v": 15127580.0
    },
    {
      "date": "2026-03-02",
      "o": 12.6,
      "h": 12.6,
      "l": 12.03,
      "c": 12.31,
      "v": 23532030.0
    },
    {
      "date": "2026-03-04",
      "o": 12.0,
      "h": 12.61,
      "l": 11.73,
      "c": 11.83,
      "v": 27830430.0
    },
    {
      "date": "2026-03-05",
      "o": 12.05,
      "h": 12.23,
      "l": 11.87,
      "c": 12.11,
      "v": 14714260.0
    },
    {
      "date": "2026-03-06",
      "o": 12.29,
      "h": 12.29,
      "l": 12.0,
      "c": 12.05,
      "v": 9911575.0
    },
    {
      "date": "2026-03-09",
      "o": 12.05,
      "h": 12.05,
      "l": 11.58,
      "c": 11.74,
      "v": 18419530.0
    },
    {
      "date": "2026-03-10",
      "o": 11.74,
      "h": 12.0,
      "l": 11.44,
      "c": 11.91,
      "v": 11383170.0
    },
    {
      "date": "2026-03-11",
      "o": 12.2,
      "h": 12.2,
      "l": 11.81,
      "c": 11.86,
      "v": 10642400.0
    },
    {
      "date": "2026-03-12",
      "o": 11.86,
      "h": 12.1,
      "l": 11.63,
      "c": 11.89,
      "v": 11055030.0
    },
    {
      "date": "2026-03-13",
      "o": 11.87,
      "h": 11.9,
      "l": 11.31,
      "c": 11.34,
      "v": 23417250.0
    },
    {
      "date": "2026-03-16",
      "o": 11.05,
      "h": 11.62,
      "l": 10.0,
      "c": 11.34,
      "v": 15138930.0
    },
    {
      "date": "2026-03-17",
      "o": 11.15,
      "h": 11.69,
      "l": 11.15,
      "c": 11.67,
      "v": 12499670.0
    },
    {
      "date": "2026-03-18",
      "o": 11.96,
      "h": 11.96,
      "l": 11.55,
      "c": 11.66,
      "v": 7713034.0
    },
    {
      "date": "2026-03-19",
      "o": 11.66,
      "h": 11.66,
      "l": 11.27,
      "c": 11.42,
      "v": 14834560.0
    },
    {
      "date": "2026-03-20",
      "o": 12.2,
      "h": 12.2,
      "l": 11.42,
      "c": 11.57,
      "v": 2449221.0
    }
  ],
  "prev_fundamentals": {},
  "yoy_fundamentals": {},
  "management": [],
  "major_shareholders": [],
  "quarterly_results": [],
  "ownership": {}
}