{
  "symbol": "PRESSTONIC",
  "fundamentals": {
    "pe_ratio": 8.23,
    "book_value": 16.9,
    "dividend_yield": 0.0,
    "roce": 8.08,
    "roe": 3.41,
    "face_value": 10.0
  },
  "fund_holdings": {
    "promoter_pct": 58.0,
    "promoter_chg": 0.0,
    "fii_pct": 0.0,
    "dii_pct": 0.0,
    "public_pct": 42.0,
    "public_chg": 0.0,
    "shareholding_updated": "2026-04-03"
  },
  "technical": {
    "close": 30.0,
    "high_52w": 121.0,
    "low_52w": 28.2
  },
  "price": 30.0,
  "breakout": {
    "high_52w": 121.0,
    "low_52w": 28.2
  },
  "quarters_screener": [
    {
      "label": "Mar 2023",
      "sales": 12.06,
      "op_profit": 4.58,
      "opm": 37.98,
      "net_profit": 2.03,
      "eps": 4.51
    },
    {
      "label": "Sep 2023",
      "sales": 14.25,
      "op_profit": 3.19,
      "opm": 22.39,
      "net_profit": 1.4,
      "eps": 1.57
    },
    {
      "label": "Mar 2024",
      "sales": 11.94,
      "op_profit": 2.45,
      "opm": 20.52,
      "net_profit": 1.13,
      "eps": 0.73
    },
    {
      "label": "Sep 2024",
      "sales": 3.08,
      "op_profit": -2.66,
      "opm": -86.36,
      "net_profit": -4.43,
      "eps": -2.88
    },
    {
      "label": "Mar 2025",
      "sales": 17.96,
      "op_profit": 7.29,
      "opm": 40.59,
      "net_profit": 5.29,
      "eps": 3.44
    },
    {
      "label": "Sep 2025",
      "sales": 20.17,
      "op_profit": 2.59,
      "opm": 12.84,
      "net_profit": 0.33,
      "eps": 0.21
    }
  ],
  "screener_updated": "2026-04-03 22:24"
}