{
  "symbol": "UNIVCABLES",
  "name": "Universal Cables Ltd.",
  "sector": "Cable",
  "industry": "Unknown",
  "price": 639.05,
  "change_pct": -2.16,
  "rsi": 43.8,
  "composite_score": -1,
  "macd": {
    "crossover": "bullish_crossover",
    "histogram": 0.59
  },
  "ema": {
    "cross_9_21": "bearish",
    "cross_50_200": "bearish",
    "ema50": 703.86,
    "ema200": 716.05
  },
  "breakout": {
    "signal": "none",
    "high_52w": 1008.0,
    "low_52w": 404.99,
    "pct_from_high": -36.6,
    "pct_from_low": 57.79
  },
  "volume": {
    "ratio": 1.33,
    "signal": "normal",
    "latest": 96515,
    "avg_20d": 72650
  },
  "bollinger": {
    "signal": "neutral"
  },
  "returns": {
    "1d": 0.0,
    "1w": 5.96,
    "1m": -9.59,
    "3m": -23.01
  },
  "fundamentals": {},
  "fund_holdings": {},
  "catalysts": [],
  "matched_scans": [
    "inside_bar_daily",
    "preset_macd_bullish_crossover",
    "preset_volume_3x_spike",
    "preset_volume_2x_spike",
    "preset_bollinger_squeeze",
    "preset_below_200_ema",
    "preset_inside_bar",
    "preset_supertrend_positive"
  ],
  "circuit": {
    "symbol": "UNIVCABLES",
    "band": "Unknown",
    "upper_limit": 0.0,
    "lower_limit": 0.0,
    "close_price": 0.0,
    "is_restricted": false,
    "band_changed": false,
    "prev_band": "",
    "change_direction": "",
    "in_fno": false
  },
  "earnings_alert": null,
  "oneil": {},
  "guru_ratings": [],
  "surveillance": {},
  "price_history": [
    {
      "date": "2025-03-19",
      "o": 468.09,
      "h": 478.73,
      "l": 464.36,
      "c": 473.26,
      "v": 68654.0
    },
    {
      "date": "2025-03-20",
      "o": 479.33,
      "h": 497.23,
      "l": 475.45,
      "c": 479.43,
      "v": 78821.0
    },
    {
      "date": "2025-03-21",
      "o": 465.61,
      "h": 512.05,
      "l": 465.61,
      "c": 507.03,
      "v": 131354.0
    },
    {
      "date": "2025-03-24",
      "o": 507.17,
      "h": 521.99,
      "l": 491.36,
      "c": 497.33,
      "v": 85410.0
    },
    {
      "date": "2025-03-25",
      "o": 500.16,
      "h": 506.08,
      "l": 478.33,
      "c": 480.92,
      "v": 76130.0
    },
    {
      "date": "2025-03-26",
      "o": 478.53,
      "h": 492.11,
      "l": 471.37,
      "c": 473.66,
      "v": 152022.0
    },
    {
      "date": "2025-03-27",
      "o": 473.36,
      "h": 520.05,
      "l": 471.37,
      "c": 508.77,
      "v": 98052.0
    },
    {
      "date": "2025-03-28",
      "o": 498.62,
      "h": 507.57,
      "l": 480.72,
      "c": 492.8,
      "v": 59143.0
    },
    {
      "date": "2025-04-01",
      "o": 493.7,
      "h": 505.68,
      "l": 490.77,
      "c": 496.38,
      "v": 19785.0
    },
    {
      "date": "2025-04-02",
      "o": 497.33,
      "h": 508.17,
      "l": 487.29,
      "c": 495.89,
      "v": 22012.0
    },
    {
      "date": "2025-04-03",
      "o": 497.13,
      "h": 507.32,
      "l": 491.41,
      "c": 494.69,
      "v": 16864.0
    },
    {
      "date": "2025-04-04",
      "o": 496.93,
      "h": 496.93,
      "l": 456.26,
      "c": 461.08,
      "v": 66714.0
    },
    {
      "date": "2025-04-07",
      "o": 435.57,
      "h": 454.67,
      "l": 419.56,
      "c": 434.13,
      "v": 40053.0
    },
    {
      "date": "2025-04-08",
      "o": 437.56,
      "h": 457.45,
      "l": 433.63,
      "c": 435.13,
      "v": 23347.0
    },
    {
      "date": "2025-04-09",
      "o": 438.56,
      "h": 440.5,
      "l": 404.99,
      "c": 408.87,
      "v": 198575.0
    },
    {
      "date": "2025-04-11",
      "o": 421.65,
      "h": 424.14,
      "l": 409.92,
      "c": 412.95,
      "v": 80871.0
    },
    {
      "date": "2025-04-15",
      "o": 420.66,
      "h": 440.84,
      "l": 418.22,
      "c": 430.5,
      "v": 73995.0
    },
    {
      "date": "2025-04-16",
      "o": 432.54,
      "h": 445.42,
      "l": 425.78,
      "c": 437.31,
      "v": 113753.0
    },
    {
      "date": "2025-04-17",
      "o": 435.57,
      "h": 457.45,
      "l": 435.52,
      "c": 446.56,
      "v": 121553.0
    },
    {
      "date": "2025-04-21",
      "o": 446.46,
      "h": 473.36,
      "l": 441.09,
      "c": 468.54,
      "v": 73989.0
    },
    {
      "date": "2025-04-22",
      "o": 468.49,
      "h": 489.17,
      "l": 460.34,
      "c": 479.13,
      "v": 99342.0
    },
    {
      "date": "2025-04-23",
      "o": 479.18,
      "h": 488.88,
      "l": 465.41,
      "c": 470.43,
      "v": 63932.0
    },
    {
      "date": "2025-04-24",
      "o": 470.43,
      "h": 484.3,
      "l": 470.43,
      "c": 478.43,
      "v": 23663.0
    },
    {
      "date": "2025-04-25",
      "o": 478.43,
      "h": 500.21,
      "l": 462.92,
      "c": 478.83,
      "v": 160570.0
    },
    {
      "date": "2025-04-28",
      "o": 471.67,
      "h": 477.09,
      "l": 464.21,
      "c": 467.59,
      "v": 28179.0
    },
    {
      "date": "2025-04-29",
      "o": 468.39,
      "h": 476.64,
      "l": 457.45,
      "c": 458.64,
      "v": 31611.0
    },
    {
      "date": "2025-04-30",
      "o": 454.52,
      "h": 460.88,
      "l": 436.97,
      "c": 443.83,
      "v": 20369.0
    },
    {
      "date": "2025-05-02",
      "o": 438.71,
      "h": 449.2,
      "l": 432.59,
      "c": 435.13,
      "v": 22572.0
    },
    {
      "date": "2025-05-05",
      "o": 436.57,
      "h": 506.88,
      "l": 436.57,
      "c": 499.12,
      "v": 627015.0
    },
    {
      "date": "2025-05-06",
      "o": 497.23,
      "h": 497.23,
      "l": 460.43,
      "c": 465.56,
      "v": 136390.0
    },
    {
      "date": "2025-05-07",
      "o": 465.56,
      "h": 475.85,
      "l": 449.0,
      "c": 461.88,
      "v": 90485.0
    },
    {
      "date": "2025-05-08",
      "o": 464.76,
      "h": 517.12,
      "l": 464.51,
      "c": 476.3,
      "v": 337956.0
    },
    {
      "date": "2025-05-09",
      "o": 472.27,
      "h": 492.06,
      "l": 459.54,
      "c": 488.38,
      "v": 66738.0
    },
    {
      "date": "2025-05-12",
      "o": 495.29,
      "h": 504.19,
      "l": 488.93,
      "c": 495.99,
      "v": 153528.0
    },
    {
      "date": "2025-05-13",
      "o": 499.02,
      "h": 534.02,
      "l": 495.24,
      "c": 526.17,
      "v": 390543.0
    },
    {
      "date": "2025-05-14",
      "o": 527.46,
      "h": 552.57,
      "l": 527.46,
      "c": 549.84,
      "v": 174074.0
    },
    {
      "date": "2025-05-15",
      "o": 551.23,
      "h": 563.21,
      "l": 537.26,
      "c": 542.03,
      "v": 87032.0
    },
    {
      "date": "2025-05-16",
      "o": 539.35,
      "h": 567.84,
      "l": 534.62,
      "c": 554.61,
      "v": 154560.0
    },
    {
      "date": "2025-05-19",
      "o": 560.88,
      "h": 620.54,
      "l": 558.29,
      "c": 576.69,
      "v": 254837.0
    },
    {
      "date": "2025-05-20",
      "o": 581.21,
      "h": 594.79,
      "l": 564.11,
      "c": 572.36,
      "v": 98956.0
    },
    {
      "date": "2025-05-21",
      "o": 575.74,
      "h": 588.57,
      "l": 567.29,
      "c": 577.38,
      "v": 63808.0
    },
    {
      "date": "2025-05-22",
      "o": 578.78,
      "h": 594.69,
      "l": 568.83,
      "c": 586.18,
      "v": 121475.0
    },
    {
      "date": "2025-05-23",
      "o": 587.73,
      "h": 620.79,
      "l": 564.85,
      "c": 610.95,
      "v": 385846.0
    },
    {
      "date": "2025-05-26",
      "o": 613.48,
      "h": 637.65,
      "l": 612.64,
      "c": 621.74,
      "v": 120716.0
    },
    {
      "date": "2025-05-27",
      "o": 623.53,
      "h": 623.53,
      "l": 606.77,
      "c": 614.97,
      "v": 50895.0
    },
    {
      "date": "2025-05-28",
      "o": 615.57,
      "h": 622.08,
      "l": 588.72,
      "c": 596.13,
      "v": 52340.0
    },
    {
      "date": "2025-05-29",
      "o": 597.47,
      "h": 605.68,
      "l": 587.03,
      "c": 589.81,
      "v": 27949.0
    },
    {
      "date": "2025-05-30",
      "o": 596.08,
      "h": 606.37,
      "l": 586.73,
      "c": 593.84,
      "v": 34632.0
    },
    {
      "date": "2025-06-02",
      "o": 584.84,
      "h": 612.39,
      "l": 584.84,
      "c": 599.96,
      "v": 40665.0
    },
    {
      "date": "2025-06-03",
      "o": 592.8,
      "h": 630.44,
      "l": 592.8,
      "c": 612.29,
      "v": 89688.0
    },
    {
      "date": "2025-06-04",
      "o": 616.91,
      "h": 624.52,
      "l": 608.36,
      "c": 616.37,
      "v": 51026.0
    },
    {
      "date": "2025-06-05",
      "o": 616.56,
      "h": 626.21,
      "l": 579.32,
      "c": 593.99,
      "v": 38873.0
    },
    {
      "date": "2025-06-06",
      "o": 596.92,
      "h": 615.77,
      "l": 596.92,
      "c": 608.76,
      "v": 30718.0
    },
    {
      "date": "2025-06-09",
      "o": 609.6,
      "h": 622.53,
      "l": 604.63,
      "c": 618.35,
      "v": 31991.0
    },
    {
      "date": "2025-06-10",
      "o": 615.57,
      "h": 651.32,
      "l": 615.57,
      "c": 648.54,
      "v": 79307.0
    },
    {
      "date": "2025-06-11",
      "o": 652.56,
      "h": 665.29,
      "l": 646.4,
      "c": 659.33,
      "v": 64393.0
    },
    {
      "date": "2025-06-12",
      "o": 661.22,
      "h": 666.29,
      "l": 631.58,
      "c": 635.96,
      "v": 40103.0
    },
    {
      "date": "2025-06-13",
      "o": 606.62,
      "h": 653.36,
      "l": 606.62,
      "c": 643.96,
      "v": 77612.0
    },
    {
      "date": "2025-06-16",
      "o": 644.01,
      "h": 661.27,
      "l": 626.76,
      "c": 656.99,
      "v": 43717.0
    },
    {
      "date": "2025-06-17",
      "o": 651.87,
      "h": 706.91,
      "l": 646.1,
      "c": 676.23,
      "v": 125342.0
    },
    {
      "date": "2025-06-18",
      "o": 681.2,
      "h": 704.92,
      "l": 667.48,
      "c": 673.05,
      "v": 78215.0
    },
    {
      "date": "2025-06-19",
      "o": 675.64,
      "h": 683.64,
      "l": 647.14,
      "c": 651.72,
      "v": 63280.0
    },
    {
      "date": "2025-06-20",
      "o": 656.94,
      "h": 698.06,
      "l": 651.37,
      "c": 681.5,
      "v": 86460.0
    },
    {
      "date": "2025-06-23",
      "o": 673.05,
      "h": 695.48,
      "l": 668.87,
      "c": 691.75,
      "v": 43610.0
    },
    {
      "date": "2025-06-24",
      "o": 702.09,
      "h": 710.79,
      "l": 686.23,
      "c": 691.55,
      "v": 43088.0
    },
    {
      "date": "2025-06-25",
      "o": 695.57,
      "h": 745.84,
      "l": 695.43,
      "c": 734.26,
      "v": 112821.0
    },
    {
      "date": "2025-06-26",
      "o": 739.38,
      "h": 767.72,
      "l": 734.96,
      "c": 764.39,
      "v": 72278.0
    },
    {
      "date": "2025-06-27",
      "o": 767.72,
      "h": 790.0,
      "l": 736.89,
      "c": 739.53,
      "v": 83046.0
    },
    {
      "date": "2025-06-30",
      "o": 735.9,
      "h": 780.55,
      "l": 716.01,
      "c": 770.51,
      "v": 62968.0
    },
    {
      "date": "2025-07-01",
      "o": 758.97,
      "h": 788.56,
      "l": 758.97,
      "c": 780.35,
      "v": 57112.0
    },
    {
      "date": "2025-07-02",
      "o": 781.65,
      "h": 785.57,
      "l": 757.33,
      "c": 769.76,
      "v": 41197.0
    },
    {
      "date": "2025-07-03",
      "o": 769.76,
      "h": 783.63,
      "l": 763.84,
      "c": 771.65,
      "v": 29037.0
    },
    {
      "date": "2025-07-04",
      "o": 770.81,
      "h": 787.61,
      "l": 763.74,
      "c": 782.39,
      "v": 40332.0
    },
    {
      "date": "2025-07-07",
      "o": 790.05,
      "h": 808.59,
      "l": 774.34,
      "c": 801.19,
      "v": 47363.0
    },
    {
      "date": "2025-07-08",
      "o": 801.19,
      "h": 819.88,
      "l": 783.73,
      "c": 790.0,
      "v": 41079.0
    },
    {
      "date": "2025-07-09",
      "o": 782.09,
      "h": 805.51,
      "l": 781.65,
      "c": 785.32,
      "v": 26815.0
    },
    {
      "date": "2025-07-10",
      "o": 791.24,
      "h": 792.04,
      "l": 770.31,
      "c": 780.4,
      "v": 15910.0
    },
    {
      "date": "2025-07-11",
      "o": 781.35,
      "h": 790.4,
      "l": 774.29,
      "c": 780.25,
      "v": 43936.0
    },
    {
      "date": "2025-07-14",
      "o": 772.45,
      "h": 785.62,
      "l": 756.98,
      "c": 765.34,
      "v": 30544.0
    },
    {
      "date": "2025-07-15",
      "o": 757.68,
      "h": 786.02,
      "l": 757.68,
      "c": 776.57,
      "v": 44511.0
    },
    {
      "date": "2025-07-16",
      "o": 778.11,
      "h": 781.84,
      "l": 765.73,
      "c": 768.47,
      "v": 17064.0
    },
    {
      "date": "2025-07-17",
      "o": 776.18,
      "h": 776.18,
      "l": 761.36,
      "c": 772.7,
      "v": 12232.0
    },
    {
      "date": "2025-07-18",
      "o": 773.79,
      "h": 780.85,
      "l": 761.11,
      "c": 766.58,
      "v": 84910.0
    },
    {
      "date": "2025-07-21",
      "o": 773.99,
      "h": 774.68,
      "l": 750.82,
      "c": 752.96,
      "v": 16069.0
    },
    {
      "date": "2025-07-22",
      "o": 760.46,
      "h": 760.76,
      "l": 732.77,
      "c": 759.02,
      "v": 36745.0
    },
    {
      "date": "2025-07-23",
      "o": 756.04,
      "h": 764.49,
      "l": 748.83,
      "c": 755.09,
      "v": 13021.0
    },
    {
      "date": "2025-07-24",
      "o": 761.61,
      "h": 761.61,
      "l": 742.76,
      "c": 744.6,
      "v": 7009.0
    },
    {
      "date": "2025-07-25",
      "o": 752.06,
      "h": 758.47,
      "l": 731.52,
      "c": 741.57,
      "v": 56368.0
    },
    {
      "date": "2025-07-28",
      "o": 741.57,
      "h": 759.72,
      "l": 706.07,
      "c": 732.62,
      "v": 53760.0
    },
    {
      "date": "2025-07-29",
      "o": 731.28,
      "h": 738.29,
      "l": 712.43,
      "c": 727.1,
      "v": 17372.0
    },
    {
      "date": "2025-07-30",
      "o": 730.93,
      "h": 736.3,
      "l": 713.77,
      "c": 721.68,
      "v": 13191.0
    },
    {
      "date": "2025-07-31",
      "o": 711.44,
      "h": 752.81,
      "l": 707.56,
      "c": 743.76,
      "v": 38035.0
    },
    {
      "date": "2025-08-01",
      "o": 739.98,
      "h": 739.98,
      "l": 708.2,
      "c": 714.47,
      "v": 11593.0
    },
    {
      "date": "2025-08-04",
      "o": 715.91,
      "h": 724.76,
      "l": 709.05,
      "c": 714.57,
      "v": 35729.0
    },
    {
      "date": "2025-08-05",
      "o": 716.56,
      "h": 729.24,
      "l": 709.85,
      "c": 718.0,
      "v": 18952.0
    },
    {
      "date": "2025-08-06",
      "o": 723.97,
      "h": 723.97,
      "l": 697.61,
      "c": 706.17,
      "v": 14889.0
    },
    {
      "date": "2025-08-07",
      "o": 699.1,
      "h": 709.75,
      "l": 686.23,
      "c": 703.53,
      "v": 15770.0
    },
    {
      "date": "2025-08-08",
      "o": 711.64,
      "h": 721.88,
      "l": 687.27,
      "c": 696.77,
      "v": 19914.0
    },
    {
      "date": "2025-08-11",
      "o": 744.85,
      "h": 764.14,
      "l": 697.61,
      "c": 735.75,
      "v": 410769.0
    },
    {
      "date": "2025-08-12",
      "o": 732.92,
      "h": 760.81,
      "l": 719.54,
      "c": 730.23,
      "v": 53123.0
    },
    {
      "date": "2025-08-13",
      "o": 730.23,
      "h": 744.4,
      "l": 723.67,
      "c": 736.15,
      "v": 55926.0
    },
    {
      "date": "2025-08-14",
      "o": 730.33,
      "h": 737.89,
      "l": 712.13,
      "c": 727.6,
      "v": 37423.0
    },
    {
      "date": "2025-08-18",
      "o": 737.89,
      "h": 741.17,
      "l": 705.07,
      "c": 708.55,
      "v": 31652.0
    },
    {
      "date": "2025-08-19",
      "o": 709.05,
      "h": 716.06,
      "l": 703.48,
      "c": 705.62,
      "v": 14373.0
    },
    {
      "date": "2025-08-20",
      "o": 712.68,
      "h": 712.68,
      "l": 702.09,
      "c": 705.72,
      "v": 61920.0
    },
    {
      "date": "2025-08-21",
      "o": 712.03,
      "h": 765.73,
      "l": 709.89,
      "c": 724.61,
      "v": 236908.0
    },
    {
      "date": "2025-08-22",
      "o": 722.97,
      "h": 728.14,
      "l": 711.04,
      "c": 712.68,
      "v": 17323.0
    },
    {
      "date": "2025-08-25",
      "o": 709.15,
      "h": 749.82,
      "l": 707.61,
      "c": 734.71,
      "v": 94726.0
    },
    {
      "date": "2025-08-26",
      "o": 734.71,
      "h": 738.59,
      "l": 714.22,
      "c": 728.24,
      "v": 39021.0
    },
    {
      "date": "2025-08-28",
      "o": 727.84,
      "h": 727.84,
      "l": 707.06,
      "c": 714.17,
      "v": 18336.0
    },
    {
      "date": "2025-08-29",
      "o": 717.01,
      "h": 721.93,
      "l": 702.19,
      "c": 708.01,
      "v": 7960.0
    },
    {
      "date": "2025-09-01",
      "o": 710.39,
      "h": 720.93,
      "l": 703.18,
      "c": 706.71,
      "v": 14318.0
    },
    {
      "date": "2025-09-02",
      "o": 709.55,
      "h": 738.54,
      "l": 705.62,
      "c": 723.17,
      "v": 35290.0
    },
    {
      "date": "2025-09-03",
      "o": 725.96,
      "h": 737.49,
      "l": 714.52,
      "c": 717.95,
      "v": 14124.0
    },
    {
      "date": "2025-09-04",
      "o": 721.0,
      "h": 755.0,
      "l": 707.0,
      "c": 711.8,
      "v": 13616.0
    },
    {
      "date": "2025-09-05",
      "o": 711.7,
      "h": 724.85,
      "l": 704.0,
      "c": 707.85,
      "v": 18235.0
    },
    {
      "date": "2025-09-08",
      "o": 710.7,
      "h": 738.3,
      "l": 708.6,
      "c": 731.55,
      "v": 39941.0
    },
    {
      "date": "2025-09-09",
      "o": 720.6,
      "h": 736.6,
      "l": 720.0,
      "c": 720.95,
      "v": 9620.0
    },
    {
      "date": "2025-09-10",
      "o": 722.8,
      "h": 736.0,
      "l": 715.65,
      "c": 720.1,
      "v": 17928.0
    },
    {
      "date": "2025-09-11",
      "o": 718.0,
      "h": 726.55,
      "l": 718.0,
      "c": 720.05,
      "v": 19099.0
    },
    {
      "date": "2025-09-12",
      "o": 724.75,
      "h": 726.5,
      "l": 715.15,
      "c": 718.4,
      "v": 10828.0
    },
    {
      "date": "2025-09-15",
      "o": 721.25,
      "h": 728.9,
      "l": 716.85,
      "c": 723.3,
      "v": 31720.0
    },
    {
      "date": "2025-09-16",
      "o": 724.75,
      "h": 731.9,
      "l": 708.1,
      "c": 711.35,
      "v": 26137.0
    },
    {
      "date": "2025-09-17",
      "o": 717.7,
      "h": 745.0,
      "l": 708.95,
      "c": 741.0,
      "v": 52471.0
    },
    {
      "date": "2025-09-18",
      "o": 750.0,
      "h": 799.0,
      "l": 750.0,
      "c": 794.2,
      "v": 280478.0
    },
    {
      "date": "2025-09-19",
      "o": 799.55,
      "h": 805.0,
      "l": 786.0,
      "c": 801.35,
      "v": 142639.0
    },
    {
      "date": "2025-09-22",
      "o": 804.0,
      "h": 823.85,
      "l": 770.05,
      "c": 774.2,
      "v": 156234.0
    },
    {
      "date": "2025-09-23",
      "o": 770.0,
      "h": 775.4,
      "l": 754.4,
      "c": 761.55,
      "v": 48103.0
    },
    {
      "date": "2025-09-24",
      "o": 770.0,
      "h": 784.4,
      "l": 741.1,
      "c": 751.8,
      "v": 47532.0
    },
    {
      "date": "2025-09-25",
      "o": 751.8,
      "h": 756.4,
      "l": 734.6,
      "c": 749.4,
      "v": 117274.0
    },
    {
      "date": "2025-09-26",
      "o": 741.9,
      "h": 749.15,
      "l": 715.6,
      "c": 717.9,
      "v": 48796.0
    },
    {
      "date": "2025-09-29",
      "o": 718.0,
      "h": 746.95,
      "l": 703.85,
      "c": 708.1,
      "v": 27015.0
    },
    {
      "date": "2025-09-30",
      "o": 710.95,
      "h": 719.35,
      "l": 705.0,
      "c": 706.85,
      "v": 12994.0
    },
    {
      "date": "2025-10-01",
      "o": 710.85,
      "h": 731.0,
      "l": 706.0,
      "c": 724.2,
      "v": 17103.0
    },
    {
      "date": "2025-10-03",
      "o": 724.2,
      "h": 730.6,
      "l": 711.0,
      "c": 715.0,
      "v": 44490.0
    },
    {
      "date": "2025-10-06",
      "o": 715.0,
      "h": 730.0,
      "l": 712.15,
      "c": 718.1,
      "v": 65124.0
    },
    {
      "date": "2025-10-07",
      "o": 724.7,
      "h": 724.7,
      "l": 704.0,
      "c": 709.35,
      "v": 78511.0
    },
    {
      "date": "2025-10-08",
      "o": 709.35,
      "h": 713.75,
      "l": 698.5,
      "c": 701.25,
      "v": 19893.0
    },
    {
      "date": "2025-10-09",
      "o": 701.25,
      "h": 712.6,
      "l": 693.95,
      "c": 702.0,
      "v": 20941.0
    },
    {
      "date": "2025-10-10",
      "o": 693.3,
      "h": 709.45,
      "l": 692.9,
      "c": 702.0,
      "v": 15569.0
    },
    {
      "date": "2025-10-13",
      "o": 698.0,
      "h": 703.9,
      "l": 676.85,
      "c": 685.55,
      "v": 126912.0
    },
    {
      "date": "2025-10-14",
      "o": 685.9,
      "h": 691.7,
      "l": 659.6,
      "c": 687.2,
      "v": 34520.0
    },
    {
      "date": "2025-10-15",
      "o": 679.9,
      "h": 692.95,
      "l": 676.6,
      "c": 687.25,
      "v": 12761.0
    },
    {
      "date": "2025-10-16",
      "o": 690.1,
      "h": 709.0,
      "l": 687.0,
      "c": 698.1,
      "v": 17818.0
    },
    {
      "date": "2025-10-17",
      "o": 701.85,
      "h": 701.85,
      "l": 675.0,
      "c": 678.7,
      "v": 18791.0
    },
    {
      "date": "2025-10-20",
      "o": 678.7,
      "h": 712.5,
      "l": 676.15,
      "c": 705.0,
      "v": 45771.0
    },
    {
      "date": "2025-10-21",
      "o": 709.7,
      "h": 721.2,
      "l": 695.8,
      "c": 709.3,
      "v": 8791.0
    },
    {
      "date": "2025-10-23",
      "o": 719.3,
      "h": 719.3,
      "l": 698.95,
      "c": 702.85,
      "v": 9688.0
    },
    {
      "date": "2025-10-24",
      "o": 703.65,
      "h": 708.35,
      "l": 701.0,
      "c": 704.25,
      "v": 5483.0
    },
    {
      "date": "2025-10-27",
      "o": 704.0,
      "h": 726.5,
      "l": 701.1,
      "c": 704.5,
      "v": 44096.0
    },
    {
      "date": "2025-10-28",
      "o": 704.0,
      "h": 710.5,
      "l": 697.55,
      "c": 701.75,
      "v": 31820.0
    },
    {
      "date": "2025-10-29",
      "o": 702.25,
      "h": 717.95,
      "l": 702.25,
      "c": 710.75,
      "v": 13453.0
    },
    {
      "date": "2025-10-30",
      "o": 711.9,
      "h": 733.5,
      "l": 706.95,
      "c": 728.15,
      "v": 26557.0
    },
    {
      "date": "2025-10-31",
      "o": 728.15,
      "h": 740.0,
      "l": 728.15,
      "c": 733.85,
      "v": 47530.0
    },
    {
      "date": "2025-11-03",
      "o": 739.0,
      "h": 739.0,
      "l": 720.0,
      "c": 727.35,
      "v": 10275.0
    },
    {
      "date": "2025-11-04",
      "o": 727.35,
      "h": 739.45,
      "l": 721.65,
      "c": 728.75,
      "v": 39771.0
    },
    {
      "date": "2025-11-06",
      "o": 729.5,
      "h": 735.25,
      "l": 717.0,
      "c": 725.9,
      "v": 54778.0
    },
    {
      "date": "2025-11-07",
      "o": 723.0,
      "h": 730.25,
      "l": 716.0,
      "c": 720.0,
      "v": 46642.0
    },
    {
      "date": "2025-11-10",
      "o": 720.7,
      "h": 739.15,
      "l": 703.0,
      "c": 709.2,
      "v": 52272.0
    },
    {
      "date": "2025-11-11",
      "o": 705.0,
      "h": 736.0,
      "l": 688.05,
      "c": 717.45,
      "v": 48054.0
    },
    {
      "date": "2025-11-12",
      "o": 722.85,
      "h": 735.0,
      "l": 717.85,
      "c": 725.1,
      "v": 9896.0
    },
    {
      "date": "2025-11-13",
      "o": 789.95,
      "h": 845.25,
      "l": 770.05,
      "c": 778.55,
      "v": 1417312.0
    },
    {
      "date": "2025-11-14",
      "o": 800.0,
      "h": 880.0,
      "l": 781.0,
      "c": 860.5,
      "v": 1857019.0
    },
    {
      "date": "2025-11-17",
      "o": 889.9,
      "h": 909.0,
      "l": 875.2,
      "c": 893.9,
      "v": 825734.0
    },
    {
      "date": "2025-11-18",
      "o": 895.0,
      "h": 923.3,
      "l": 891.1,
      "c": 899.55,
      "v": 330356.0
    },
    {
      "date": "2025-11-19",
      "o": 906.0,
      "h": 924.7,
      "l": 885.0,
      "c": 918.35,
      "v": 250153.0
    },
    {
      "date": "2025-11-20",
      "o": 918.35,
      "h": 1008.0,
      "l": 908.7,
      "c": 977.6,
      "v": 1415945.0
    },
    {
      "date": "2025-11-21",
      "o": 967.4,
      "h": 988.8,
      "l": 947.8,
      "c": 958.6,
      "v": 181539.0
    },
    {
      "date": "2025-11-24",
      "o": 958.05,
      "h": 958.45,
      "l": 917.1,
      "c": 924.55,
      "v": 190204.0
    },
    {
      "date": "2025-11-25",
      "o": 931.8,
      "h": 939.9,
      "l": 902.4,
      "c": 907.75,
      "v": 88491.0
    },
    {
      "date": "2025-11-26",
      "o": 910.15,
      "h": 963.0,
      "l": 899.0,
      "c": 934.5,
      "v": 259093.0
    },
    {
      "date": "2025-11-27",
      "o": 929.75,
      "h": 949.0,
      "l": 916.0,
      "c": 929.8,
      "v": 73154.0
    },
    {
      "date": "2025-11-28",
      "o": 929.8,
      "h": 970.0,
      "l": 915.15,
      "c": 956.3,
      "v": 135380.0
    },
    {
      "date": "2025-12-01",
      "o": 975.1,
      "h": 990.0,
      "l": 940.0,
      "c": 960.95,
      "v": 159854.0
    },
    {
      "date": "2025-12-02",
      "o": 957.0,
      "h": 971.7,
      "l": 942.95,
      "c": 967.75,
      "v": 112532.0
    },
    {
      "date": "2025-12-03",
      "o": 965.0,
      "h": 1008.0,
      "l": 948.6,
      "c": 958.2,
      "v": 229927.0
    },
    {
      "date": "2025-12-04",
      "o": 959.2,
      "h": 961.8,
      "l": 919.8,
      "c": 924.6,
      "v": 147595.0
    },
    {
      "date": "2025-12-05",
      "o": 924.6,
      "h": 930.15,
      "l": 902.0,
      "c": 907.25,
      "v": 86506.0
    },
    {
      "date": "2025-12-08",
      "o": 905.0,
      "h": 924.65,
      "l": 879.8,
      "c": 889.5,
      "v": 118602.0
    },
    {
      "date": "2025-12-09",
      "o": 876.15,
      "h": 913.35,
      "l": 866.55,
      "c": 892.3,
      "v": 137424.0
    },
    {
      "date": "2025-12-10",
      "o": 891.0,
      "h": 938.7,
      "l": 888.6,
      "c": 896.55,
      "v": 99752.0
    },
    {
      "date": "2025-12-11",
      "o": 893.35,
      "h": 910.0,
      "l": 876.0,
      "c": 906.85,
      "v": 62237.0
    },
    {
      "date": "2025-12-12",
      "o": 906.85,
      "h": 938.0,
      "l": 891.35,
      "c": 895.25,
      "v": 66367.0
    },
    {
      "date": "2025-12-15",
      "o": 885.1,
      "h": 908.65,
      "l": 877.1,
      "c": 895.35,
      "v": 57517.0
    },
    {
      "date": "2025-12-16",
      "o": 898.0,
      "h": 908.25,
      "l": 883.0,
      "c": 896.65,
      "v": 44926.0
    },
    {
      "date": "2025-12-17",
      "o": 896.65,
      "h": 896.65,
      "l": 831.4,
      "c": 842.15,
      "v": 111049.0
    },
    {
      "date": "2025-12-18",
      "o": 842.15,
      "h": 852.45,
      "l": 825.1,
      "c": 830.05,
      "v": 68052.0
    },
    {
      "date": "2025-12-19",
      "o": 831.9,
      "h": 871.05,
      "l": 827.0,
      "c": 856.15,
      "v": 128562.0
    },
    {
      "date": "2025-12-22",
      "o": 869.65,
      "h": 903.05,
      "l": 862.0,
      "c": 893.25,
      "v": 138064.0
    },
    {
      "date": "2025-12-23",
      "o": 903.9,
      "h": 905.0,
      "l": 882.0,
      "c": 891.45,
      "v": 37959.0
    },
    {
      "date": "2025-12-24",
      "o": 891.45,
      "h": 902.05,
      "l": 879.0,
      "c": 889.2,
      "v": 71402.0
    },
    {
      "date": "2025-12-26",
      "o": 894.0,
      "h": 899.2,
      "l": 870.6,
      "c": 881.55,
      "v": 58353.0
    },
    {
      "date": "2025-12-29",
      "o": 875.0,
      "h": 894.25,
      "l": 856.0,
      "c": 859.25,
      "v": 74383.0
    },
    {
      "date": "2025-12-30",
      "o": 858.0,
      "h": 898.0,
      "l": 849.3,
      "c": 890.5,
      "v": 65342.0
    },
    {
      "date": "2025-12-31",
      "o": 886.95,
      "h": 902.95,
      "l": 884.2,
      "c": 888.5,
      "v": 35900.0
    },
    {
      "date": "2026-01-01",
      "o": 889.9,
      "h": 969.0,
      "l": 889.9,
      "c": 957.9,
      "v": 375378.0
    },
    {
      "date": "2026-01-02",
      "o": 946.6,
      "h": 963.7,
      "l": 930.15,
      "c": 956.9,
      "v": 113000.0
    },
    {
      "date": "2026-01-05",
      "o": 961.0,
      "h": 981.1,
      "l": 935.0,
      "c": 940.15,
      "v": 84132.0
    },
    {
      "date": "2026-01-06",
      "o": 941.5,
      "h": 948.95,
      "l": 916.3,
      "c": 932.9,
      "v": 48582.0
    },
    {
      "date": "2026-01-07",
      "o": 939.9,
      "h": 962.0,
      "l": 906.1,
      "c": 929.55,
      "v": 119471.0
    },
    {
      "date": "2026-01-08",
      "o": 925.0,
      "h": 928.5,
      "l": 855.1,
      "c": 865.1,
      "v": 132071.0
    },
    {
      "date": "2026-01-09",
      "o": 860.0,
      "h": 888.25,
      "l": 835.0,
      "c": 841.1,
      "v": 116939.0
    },
    {
      "date": "2026-01-12",
      "o": 840.0,
      "h": 840.0,
      "l": 807.6,
      "c": 825.35,
      "v": 106385.0
    },
    {
      "date": "2026-01-13",
      "o": 826.1,
      "h": 831.45,
      "l": 795.25,
      "c": 805.75,
      "v": 73578.0
    },
    {
      "date": "2026-01-14",
      "o": 800.1,
      "h": 800.1,
      "l": 750.25,
      "c": 755.45,
      "v": 202453.0
    },
    {
      "date": "2026-01-15",
      "o": 755.45,
      "h": 755.45,
      "l": 755.45,
      "c": 755.45,
      "v": 0.0
    },
    {
      "date": "2026-01-16",
      "o": 764.3,
      "h": 776.0,
      "l": 732.15,
      "c": 738.15,
      "v": 168916.0
    },
    {
      "date": "2026-01-19",
      "o": 730.0,
      "h": 761.4,
      "l": 721.5,
      "c": 737.1,
      "v": 71986.0
    },
    {
      "date": "2026-01-20",
      "o": 735.0,
      "h": 735.0,
      "l": 685.0,
      "c": 689.3,
      "v": 102229.0
    },
    {
      "date": "2026-01-21",
      "o": 690.95,
      "h": 729.35,
      "l": 670.0,
      "c": 696.25,
      "v": 122132.0
    },
    {
      "date": "2026-01-22",
      "o": 705.0,
      "h": 714.2,
      "l": 687.6,
      "c": 702.0,
      "v": 60922.0
    },
    {
      "date": "2026-01-23",
      "o": 702.0,
      "h": 702.0,
      "l": 664.0,
      "c": 666.2,
      "v": 50767.0
    },
    {
      "date": "2026-01-27",
      "o": 666.0,
      "h": 684.0,
      "l": 641.7,
      "c": 669.15,
      "v": 62025.0
    },
    {
      "date": "2026-01-28",
      "o": 675.0,
      "h": 710.0,
      "l": 674.8,
      "c": 703.45,
      "v": 67119.0
    },
    {
      "date": "2026-01-29",
      "o": 710.0,
      "h": 742.0,
      "l": 699.5,
      "c": 734.85,
      "v": 79710.0
    },
    {
      "date": "2026-01-30",
      "o": 733.95,
      "h": 744.6,
      "l": 705.5,
      "c": 726.85,
      "v": 47542.0
    },
    {
      "date": "2026-02-02",
      "o": 703.0,
      "h": 710.0,
      "l": 680.4,
      "c": 697.6,
      "v": 39757.0
    },
    {
      "date": "2026-02-03",
      "o": 734.0,
      "h": 763.8,
      "l": 721.7,
      "c": 733.55,
      "v": 128125.0
    },
    {
      "date": "2026-02-04",
      "o": 743.5,
      "h": 772.0,
      "l": 732.5,
      "c": 768.1,
      "v": 91162.0
    },
    {
      "date": "2026-02-05",
      "o": 773.6,
      "h": 778.0,
      "l": 754.6,
      "c": 759.9,
      "v": 63724.0
    },
    {
      "date": "2026-02-06",
      "o": 752.3,
      "h": 770.0,
      "l": 724.95,
      "c": 758.15,
      "v": 63952.0
    },
    {
      "date": "2026-02-09",
      "o": 742.6,
      "h": 754.9,
      "l": 699.9,
      "c": 735.15,
      "v": 192234.0
    },
    {
      "date": "2026-02-10",
      "o": 738.0,
      "h": 743.95,
      "l": 725.65,
      "c": 734.0,
      "v": 58641.0
    },
    {
      "date": "2026-02-11",
      "o": 737.0,
      "h": 737.0,
      "l": 711.8,
      "c": 714.85,
      "v": 39708.0
    },
    {
      "date": "2026-02-12",
      "o": 706.0,
      "h": 719.5,
      "l": 699.0,
      "c": 700.1,
      "v": 38052.0
    },
    {
      "date": "2026-02-13",
      "o": 690.05,
      "h": 705.55,
      "l": 679.9,
      "c": 690.2,
      "v": 40374.0
    },
    {
      "date": "2026-02-16",
      "o": 690.05,
      "h": 705.0,
      "l": 679.35,
      "c": 683.9,
      "v": 49746.0
    },
    {
      "date": "2026-02-17",
      "o": 692.55,
      "h": 703.9,
      "l": 680.8,
      "c": 694.25,
      "v": 30368.0
    },
    {
      "date": "2026-02-18",
      "o": 692.3,
      "h": 712.55,
      "l": 692.3,
      "c": 706.85,
      "v": 32078.0
    },
    {
      "date": "2026-02-19",
      "o": 706.85,
      "h": 709.6,
      "l": 691.15,
      "c": 698.35,
      "v": 46670.0
    },
    {
      "date": "2026-02-20",
      "o": 698.35,
      "h": 698.35,
      "l": 675.05,
      "c": 682.7,
      "v": 22266.0
    },
    {
      "date": "2026-02-23",
      "o": 685.0,
      "h": 701.45,
      "l": 664.3,
      "c": 673.6,
      "v": 31518.0
    },
    {
      "date": "2026-02-24",
      "o": 670.0,
      "h": 690.85,
      "l": 660.2,
      "c": 677.1,
      "v": 35951.0
    },
    {
      "date": "2026-02-25",
      "o": 675.1,
      "h": 694.95,
      "l": 673.0,
      "c": 676.6,
      "v": 30697.0
    },
    {
      "date": "2026-02-26",
      "o": 675.55,
      "h": 697.05,
      "l": 675.55,
      "c": 685.3,
      "v": 50449.0
    },
    {
      "date": "2026-02-27",
      "o": 689.95,
      "h": 710.95,
      "l": 670.0,
      "c": 694.85,
      "v": 142530.0
    },
    {
      "date": "2026-03-02",
      "o": 661.5,
      "h": 694.0,
      "l": 660.0,
      "c": 685.05,
      "v": 64593.0
    },
    {
      "date": "2026-03-04",
      "o": 670.0,
      "h": 681.35,
      "l": 664.55,
      "c": 668.4,
      "v": 48914.0
    },
    {
      "date": "2026-03-05",
      "o": 677.0,
      "h": 680.5,
      "l": 667.25,
      "c": 675.65,
      "v": 35198.0
    },
    {
      "date": "2026-03-06",
      "o": 682.5,
      "h": 684.7,
      "l": 670.35,
      "c": 678.35,
      "v": 22819.0
    },
    {
      "date": "2026-03-09",
      "o": 674.2,
      "h": 674.55,
      "l": 647.0,
      "c": 649.65,
      "v": 31319.0
    },
    {
      "date": "2026-03-10",
      "o": 663.95,
      "h": 670.0,
      "l": 643.05,
      "c": 647.55,
      "v": 80931.0
    },
    {
      "date": "2026-03-11",
      "o": 649.8,
      "h": 660.0,
      "l": 621.1,
      "c": 623.3,
      "v": 82873.0
    },
    {
      "date": "2026-03-12",
      "o": 617.0,
      "h": 655.95,
      "l": 605.05,
      "c": 634.4,
      "v": 69288.0
    },
    {
      "date": "2026-03-13",
      "o": 630.0,
      "h": 631.7,
      "l": 600.0,
      "c": 603.1,
      "v": 42590.0
    },
    {
      "date": "2026-03-16",
      "o": 600.0,
      "h": 606.15,
      "l": 576.0,
      "c": 584.55,
      "v": 80720.0
    },
    {
      "date": "2026-03-17",
      "o": 583.8,
      "h": 602.0,
      "l": 582.55,
      "c": 589.1,
      "v": 37490.0
    },
    {
      "date": "2026-03-18",
      "o": 592.65,
      "h": 665.95,
      "l": 590.05,
      "c": 653.15,
      "v": 399679.0
    },
    {
      "date": "2026-03-19",
      "o": 639.0,
      "h": 665.8,
      "l": 626.6,
      "c": 639.05,
      "v": 96515.0
    }
  ],
  "prev_fundamentals": {},
  "yoy_fundamentals": {},
  "management": [],
  "major_shareholders": [],
  "quarterly_results": [],
  "ownership": {}
}